mosiac/__init__.py
mosiac-0.0.2.dist-info/LICENSE
mosiac-0.0.2.dist-info/METADATA
mosiac-0.0.2.dist-info/WHEEL
mosiac-0.0.2.dist-info/top_level.txt
mosiac-0.0.2.dist-info/RECORD
