Metadata-Version: 2.1
Name: mosiac
Version: 0.0.2
Summary: Coming soon
Author: quincr
Project-URL: Homepage, https://github.com/quincr/mosiac
License-File: LICENSE
